{
  "version": "5",
  "dialect": "pg",
  "id": "547a98c3-5459-4bf2-8c04-652ab28a57e7",
  "prevId": "00000000-0000-0000-0000-000000000000",
  "tables": {
    "client": {
      "name": "client",
      "schema": "",
      "columns": {
        "id": {
          "name": "id",
          "type": "uuid",
          "primaryKey": true,
          "notNull": true,
          "default": "gen_random_uuid()"
        },
        "email_address": {
          "name": "email_address",
          "type": "text",
          "primaryKey": false,
          "notNull": true
        }
      },
      "indexes": {
        "email_idx": {
          "name": "email_idx",
          "columns": [
            "email_address"
          ],
          "isUnique": true
        }
      },
      "foreignKeys": {},
      "compositePrimaryKeys": {},
      "uniqueConstraints": {}
    }
  },
  "enums": {},
  "schemas": {},
  "_meta": {
    "schemas": {},
    "tables": {},
    "columns": {}
  }
}